mnemocards/__init__.py
mnemocards/__main__.py
mnemocards/_argument_parser.py
mnemocards/_version.py
mnemocards/assets/css/autogenerate.css
mnemocards/assets/css/highlight/.gitignore
mnemocards/assets/css/highlight/github.css
mnemocards/assets/css/highlight/makefile
mnemocards/assets/css/markdown_github.css
mnemocards/assets/css/markdown_modest.css
mnemocards/assets/css/vocabulary.css
mnemocards/builders/__init__.py
mnemocards/builders/autogenerate_builder.py
mnemocards/builders/expression_builder.py
mnemocards/builders/markdown_card_builder.py
mnemocards/builders/vocabulary_builder.py
mnemocards/clean.py
mnemocards/generate.py
mnemocards/github.py
mnemocards/import_command.py
mnemocards/maketsv.py
mnemocards/pull.py
mnemocards/push.py
mnemocards/utils.py
mnemocards-0.1.5.dist-info/entry_points.txt
mnemocards-0.1.5.dist-info/LICENSE
mnemocards-0.1.5.dist-info/WHEEL
mnemocards-0.1.5.dist-info/METADATA
mnemocards-0.1.5.dist-info/RECORD
