Metadata-Version: 2.1
Name: mnemocards
Version: 0.1.5
Summary: Flashcards generator. You won't forget anything...
Home-page: https://github.com/guiferviz/mnemocards
License: MIT
Keywords: anki,cards,flashcards,memorization,generator
Author: guiferviz
Author-email: guiferviz@gmail.com
Requires-Python: >=3.8,<4.0
Classifier: License :: OSI Approved :: MIT License
Classifier: Programming Language :: Python :: 3
Classifier: Programming Language :: Python :: 3.8
Classifier: Programming Language :: Python :: 3.9
Classifier: Topic :: Education
Classifier: Topic :: Software Development :: Libraries :: Python Modules
Requires-Dist: PyGithub (>=1.55,<2.0)
Requires-Dist: Pygments (>=2.10.0,<3.0.0)
Requires-Dist: anki (>=2.1.33,<3.0.0)
Requires-Dist: gTTS (>=2.2.3,<3.0.0)
Requires-Dist: genanki-mnemocards (>=0.11.0,<0.12.0)
Requires-Dist: googletrans (==3.1.0a0)
Requires-Dist: iso-639 (>=0.4.5,<0.5.0)
Requires-Dist: markdown2 (>=2.4.1,<3.0.0)
Requires-Dist: pykakasi (>=2.0.4,<3.0.0)
Project-URL: Repository, https://github.com/guiferviz/mnemocards
